skippy/__init__.py
skippy/core/__init__.py
skippy/core/clustercontext.py
skippy/core/model.py
skippy/core/predicates.py
skippy/core/priorities.py
skippy/core/scheduler.py
skippy/core/storage.py
skippy/core/utils.py
tests/__init__.py
tests/skippy/__init__.py
tests/skippy/core/__init__.py
tests/skippy/core/test_utils.py
edgerun_skippy_core-0.1.1.dist-info/METADATA
edgerun_skippy_core-0.1.1.dist-info/WHEEL
edgerun_skippy_core-0.1.1.dist-info/top_level.txt
edgerun_skippy_core-0.1.1.dist-info/RECORD
