Metadata-Version: 2.1
Name: edgerun-skippy-core
Version: 0.1.1
Summary: Skippy scheduler core
Home-page: https://github.com/edgerun/skippy-core
Author: Alexander Rashed, Thomas Rausch
Author-email: alexander.rashed@gmail.com, t.rausch@dsg.tuwien.ac.at
License: UNKNOWN
Download-URL: https://github.com/edgerun/skippy-core
Platform: UNKNOWN
Classifier: Programming Language :: Python :: 3.7
Classifier: License :: OSI Approved :: MIT License
Classifier: Operating System :: OS Independent
Classifier: Development Status :: 4 - Beta
